cylinter/__init__.py
cylinter/components.py
cylinter/config.py
cylinter/cylinter.py
cylinter/pipeline.py
cylinter/prep.py
cylinter/utils.py
cylinter-0.0.44.data/data/config.yml
cylinter-0.0.44.data/data/prep_subprocess.sh
cylinter-0.0.44.dist-info/LICENSE
cylinter-0.0.44.dist-info/METADATA
cylinter-0.0.44.dist-info/WHEEL
cylinter-0.0.44.dist-info/entry_points.txt
cylinter-0.0.44.dist-info/top_level.txt
cylinter-0.0.44.dist-info/RECORD
