Metadata-Version: 2.1
Name: cylinter
Version: 0.0.44
Summary: CyLinter
Home-page: https://github.com/labsyspharm/cylinter
Author: Gregory J. Baker
Author-email: gregory_baker2@hms.harvard.edu
License: MIT License
Download-URL: https://github.com/labsyspharm/cylinter/archive/v0.0.44.tar.gz
Keywords: scripts single cell data science
Platform: UNKNOWN
Classifier: Development Status :: 4 - Beta
Classifier: Intended Audience :: End Users/Desktop
Classifier: Intended Audience :: Science/Research
Classifier: License :: OSI Approved :: MIT License
Classifier: Natural Language :: English
Classifier: Operating System :: OS Independent
Classifier: Programming Language :: Python :: 3
Classifier: Topic :: Scientific/Engineering :: Visualization
Requires-Python: >=3.6.0
License-File: LICENSE
Requires-Dist: numba (==0.53.1)
Requires-Dist: PyYAML (==5.4)
Requires-Dist: pyarrow (==5.0.0)
Requires-Dist: pandas (>=1.1.5)
Requires-Dist: hdbscan (==0.8.26)
Requires-Dist: joblib (==0.17.0)
Requires-Dist: matplotlib (==3.3.3)
Requires-Dist: seaborn (==0.11.1)
Requires-Dist: scikit-learn (==0.24.2)
Requires-Dist: scikit-image (==0.18.1)
Requires-Dist: napari (==0.4.10)
Requires-Dist: PyQt5 (==5.15.2)
Requires-Dist: zarr (==2.6.1)
Requires-Dist: natsort (==7.1.0)
Requires-Dist: umap-learn (==0.5.1)
Requires-Dist: hurry.filesize (==0.9)
Requires-Dist: synapseclient (==2.4.0)
Requires-Dist: pyparsing (==2.0.3)
Requires-Dist: PyOpenGL-accelerate
Requires-Dist: cellcutter (>=0.2.6)
